californiavirtualcampusapi-0.0.2.dist-info/licenses/LICENSE
cvc/__init__.py
cvc/course.py
cvc/courseSection.py
cvc/helperFunctions.py
cvc/sharedVariables.py
californiavirtualcampusapi-0.0.2.dist-info/METADATA
californiavirtualcampusapi-0.0.2.dist-info/WHEEL
californiavirtualcampusapi-0.0.2.dist-info/top_level.txt
californiavirtualcampusapi-0.0.2.dist-info/RECORD
