Metadata-Version: 2.4
Name: CaliforniaVirtualCampusAPI
Version: 0.0.2
Summary: A simple API for the California Virtual Campus platform.
Home-page: https://github.com/rob-m1/california-virtual-campus-api
Author: Robert Meli
Author-email: Robert Meli <robertmeli1@outlook.com>
Project-URL: Homepage, https://github.com/rob-m1/california-virtual-campus-api
Project-URL: Issues, https://github.com/rob-m1/california-virtual-campus-api/issues
Classifier: Programming Language :: Python :: 3
Classifier: Operating System :: OS Independent
Classifier: Development Status :: 3 - Alpha
Classifier: Intended Audience :: Developers
Classifier: License :: OSI Approved :: Apache Software License
Requires-Python: >=3.8
License-File: LICENSE
Requires-Dist: Requests
Requires-Dist: beautifulsoup4
Requires-Dist: selenium
Requires-Dist: setuptools
Requires-Dist: textdistance
Dynamic: author
Dynamic: home-page
Dynamic: license-file
